{
  "users": [
    {
      "login": "testerww",
      "name": "Testnames",
      "password": "qwerty",
      "picture": "https://picsum.photos/seed/a2a35be5-c922-48a8-af7f-6a9e53a746b5/300",
      "id": 2
    },
    {
      "login": "Helper",
      "name": "Helpersssdfsf",
      "password": "qwerty",
      "picture": "https://picsum.photos/seed/fe761fd4-60bc-4aa9-8bb7-6b8375be9470/300",
      "id": 3
    },
    {
      "login": "Admin",
      "name": "tester",
      "password": "qwerty",
      "picture": "https://picsum.photos/seed/75e474ae-d5ed-4366-989f-2be90889a630/300",
      "id": 4
    }
  ]
}